hasaki/__init__.py
hasaki/utlis/__init__.py
hasaki/utlis/tools.py
hasaki-0.0.2.dist-info/LICENSE
hasaki-0.0.2.dist-info/METADATA
hasaki-0.0.2.dist-info/WHEEL
hasaki-0.0.2.dist-info/top_level.txt
hasaki-0.0.2.dist-info/RECORD
